certbot_dns_spaceship/__init__.py
certbot_dns_spaceship/authenticator.py
certbot_dns_spaceship/client.py
certbot_dns_spaceship-1.0.4.dist-info/LICENSE
certbot_dns_spaceship-1.0.4.dist-info/METADATA
certbot_dns_spaceship-1.0.4.dist-info/WHEEL
certbot_dns_spaceship-1.0.4.dist-info/entry_points.txt
certbot_dns_spaceship-1.0.4.dist-info/top_level.txt
certbot_dns_spaceship-1.0.4.dist-info/RECORD
