Metadata-Version: 2.2
Name: certbot-dns-spaceship
Version: 1.0.4
Summary: Spaceship DNS Authenticator plugin for Certbot
Home-page: https://github.com/version-two/certbot_dns_spaceship
Author: Mario Chamuty
Author-email: Mario Chamuty <info@versiontwo.sk>
License: Apache-2.0
Keywords: certbot,dns,spaceship,authentication
Classifier: Development Status :: 5 - Production/Stable
Classifier: Intended Audience :: Developers
Classifier: License :: OSI Approved :: Apache Software License
Classifier: Programming Language :: Python :: 3
Classifier: Programming Language :: Python :: 3.7
Classifier: Programming Language :: Python :: 3.8
Classifier: Programming Language :: Python :: 3.9
Classifier: Programming Language :: Python :: 3.10
Classifier: Programming Language :: Python :: 3.11
Classifier: Topic :: Internet :: WWW/HTTP
Classifier: Topic :: Security :: Cryptography
Requires-Python: >=3.7
License-File: LICENSE
Requires-Dist: certbot>=1.0.0
Requires-Dist: requests
Requires-Dist: tldextract
Provides-Extra: dev
Requires-Dist: pytest; extra == "dev"
Requires-Dist: twine; extra == "dev"
Requires-Dist: flake8; extra == "dev"
Dynamic: author
Dynamic: home-page
